Workbook

Sheet 路线与门槛
A1: 荷兰迁居计划
A2: 规则核验日 | B2: 46283 | C2: 计划开始日 | D2: 46286 | E2: 适用路线 | F2: 荷兰高技术移民（HSM）工作居留；不是欧盟蓝卡，也不是加拿大积分制。
A3: 优先目标 | B3: 荷兰：先验证雇主与岗位 | C3: 工作居留主申 | D3: 丈夫；妻子申请家庭居留 | E3: 备选 | F3: 爱尔兰；启用时单独核实职业、学历与工资。
A4: 填写说明 | B4: 浅黄色单元格可填写或更新；公式格无需改写。 | C4: 时间假设 | D4: 丈夫每周英语8小时，另加求职2小时；妻子英语5小时。 | E4: 计划边界 | F4: 六个月是首轮准备与验证期，不是获聘或获签承诺。未知资料均按待确认处理。
A6: 性质 | B6: 项目 | C6: 目前情况 | D6: 目标或门槛 | E6: 验收与处理 | F6: 依据
A7: 签证硬条件 | B7: 移民积分 | C7: 不适用 | D7: 没有65分或CRS门槛 | E7: 不计算“总移民分”；按HSM每项条件核对。 | F7: https://ind.nl/en/residence-permits/work/highly-skilled-migrant
A8: 签证硬条件 | B8: 雇主与合同 | C8: 尚无已确认聘用 | D8: 荷兰工作合同；雇主获IND认可 | E8: 查实际签约主体的法定名称；认可资质不等于愿意为本岗位办理。 | F8: https://ind.nl/en/residence-permits/work/highly-skilled-migrant https://ind.nl/en/public-register-recognised-sponsors
A9: 签证硬条件 | B9: 30岁及以上工资 | C9: 本人31岁；报价未知 | D9: 2026年税前每月至少€5,942，不含假期津贴 | E9: 2027年申请前更新标准；核实每月可计入金额、市场合理性。不要用含奖金总包直接比较。 | F9: https://ind.nl/en/required-amounts-income-requirements
A10: 签证硬条件 | B10: 英语考试 | C10: 夫妻均六级；当前水平未知 | D10: HSM没有统一雅思最低分 | E10: 六级不能换算雅思；公司英语标准由职位与面试决定。 | F10: https://ind.nl/en/residence-permits/work/highly-skilled-migrant
A11: 招聘要求 | B11: 学历与相关经验 | C11: 能源与动力工程本科、有学位；汽车嵌入式7年 | D11: 按实际招聘要求核验 | E11: HSM并非ACS评估；学历要求与职位适配由雇主核实。不能仅凭7年认定高级岗位薪资达标。 | F11: https://ind.nl/en/residence-permits/work/highly-skilled-migrant
A12: 学习建议 | B12: 丈夫英语 | C12: 先做听说与完整模拟摸底 | D12: 可选标尺：雅思总分6.5、听力7.0、口语6.5、其余不低于6.0 | E12: 仅学习参考，非签证门槛；真实技术面试表现优先。没有达到参考分也可投递。 | F12: 规划建议；不是官方分数要求。
A13: 学习建议 | B13: 妻子英语 | C13: 25岁，金融硕士，运营工作1年 | D13: 先能完成日常事务和20分钟工作交流 | E13: 若需要数字标尺，可参考总分6.0、口语6.0；不是配偶签证要求，也不保证就业。 | F13: 规划建议；不是官方分数要求。
A14: 家庭居留 | B14: 配偶随行及工作 | C14: 已婚；证件待整理 | D14: 另行申请家庭居留并满足关系等条件 | E14: 取得HSM配偶对应居留可自由受雇；不需要先找到工作。初期家庭预算按丈夫单收入测算。 | F14: https://ind.nl/en/residence-permits/family-and-partner/residence-permit-for-partner
A15: 长期居留 | B15: 年限与合规 | C15: 尚未开始在荷居留 | D15: 现行一般路径：连续合法居留至少5年 | E15: 从符合条件的居留时间计算，不从今天或学英语开始。夫妻分别核实年限和其他条件。 | F15: https://ind.nl/en/replace-extend-renew-and-change/permanent-residency/permanent-residence-permit
... A20: 工资核对 | B20: 金额（欧元） | C20: 口径 | D20: 说明 | E20: 规则年份 | F20: 来源
A21: 官方月薪参考 | B21: 5942 | C21: 税前；不含假期津贴 | D21: 仅2026年、首次按30岁及以上标准核对 | E21: 2026 | F21: https://ind.nl/en/required-amounts-income-requirements
A22: 你的拟议月薪 | C22: 按官方可计入口径 | D22: 留空表示还没有符合口径的报价；须与HR核实。 | F22: 待填写
A23: 参考年薪折算 | B23: =B21*12 -> 71304 | C23: 月门槛×12 | D23: 只用于理解量级；正式审核不能只看全年总包。 | F23: 公式
A24: 月薪差额 | B24: =IF(B22="","",B22-B21) | C24: 拟议月薪－参考月门槛 | D24: 正数仅表示数值高于参考，不代表获签；2027须先更新月门槛。 | F24: 公式
A25: 预算建议 | B25: 另做单收入预算 | C25: 丈夫税后收入－房租－保险－生活费－国内固定支出 | D25: 按真实城市和offer测算；迁居储备可按一次性费用＋6个月必要开支规划，6个月为建议非签证要求。 | F25: 规划建议
A26: 尚缺输入 | B26: 本人英语摸底、技术职责、每周可用时间 | C26: 妻子职责、家庭支出、可接受城市与转岗范围 | D26: 这些资料补齐后调整阶段目标；不据此虚构成功率。 | F26: 用户信息尚未提供
A28: 下一次复核 | B28: 每次正式申请前 | C28: 年度工资与政策更新 | D28: 本文件不自动联网更新 | E28: 计划启动 | F28: 先做摸底、简历及雇主验证

Sheet 阶段计划
A1: 阶段计划
A2: 时间口径 | B2: 前26周为首轮准备；后续求职可延长。 | C2: 职责 | D2: 丈夫为技术求职主力 | E2: 原则 | F2: 岗位验证与英语学习同时进行。 | G2: 更新 | H2: 状态栏可改
A4: 阶段 | B4: 计划开始 | C4: 计划结束 | D4: 丈夫的主要任务 | E4: 妻子与家庭任务 | F4: 阶段验收 | G4: 复盘或调整条件 | H4: 完成状态
A5: 第1—2周 | B5: =路线与门槛!$D$2+0 -> 46286 | C5: =路线与门槛!$D$2+13 -> 46299 | D5: 完成听说摸底；建立英文简历；梳理2个核心项目；收集约15个真实岗位样本。 | E5: 核对学历、婚姻及护照材料；妻子记录真实运营职责。 | F5: 有英语基线、简历初稿、技能差距表；初步核对雇主与工资可行性。 | G5: 如岗位多卡在技术或薪资，先调整目标岗位；不等待语言学完。 | H5: 未开始
A6: 第3—8周 | B6: =路线与门槛!$D$2+14 -> 46300 | C6: =路线与门槛!$D$2+55 -> 46341 | D6: 每周8小时英语＋2小时求职；完善2个项目故事；每周投约2—3个真正匹配岗位。 | E6: 妻子每周5小时英语，保留工作并积累成果。 | F6: 能做3分钟自我介绍、10分钟项目讲解；开始记录招聘回复。 | G6: 第8周复盘：简历无回复看匹配与担保；交流困难看听说。 | H6: 未开始
A7: 第9—14周 | B7: =路线与门槛!$D$2+56 -> 46342 | C7: =路线与门槛!$D$2+97 -> 46383 | D7: 每周1次模拟面试；复习职位要求涉及的C/MCU/通信/调试等；每周约3—5次精准投递。 | E7: 形成单收入生活预算草稿；只补明确要求的资料。 | F7: 完成30分钟英语技术问答；在追问下解释故障定位和设计取舍。 | G7: 第14周复盘：如果招聘反馈持续指向薪资或担保，增加爱尔兰验证。 | H7: 未开始
A8: 第15—26周 | B8: =路线与门槛!$D$2+98 -> 46384 | C8: =路线与门槛!$D$2+181 -> 46467 | D8: 继续面试、复盘与补短板；可做一次雅思完整模拟衡量变化；筛选合同和真实岗位。 | E8: 夫妻共同核对城市、工作时间、家庭预算及妻子就业空间。 | F8: 能进行45分钟技术模拟；有可追踪的岗位与反馈记录。学习参考分见语言表。 | G8: 第26周正式决策：继续荷兰、调整岗位、启用备选或延长语言准备。 | H8: 未开始
A9: 第27—52周（按需） | B9: =路线与门槛!$D$2+182 -> 46468 | C9: =路线与门槛!$D$2+363 -> 46649 | D9: 根据明确瓶颈延长求职或语言训练；每6—8周复盘；保持原工作与收入。 | E9: 备选国家需重新核验签证条件，英文材料可复用。 | F9: 有更充分的招聘反馈和岗位适配证据；不以时间到期推定应有offer。 | G9: 若没有有效进展，找原因后缩小或改变方向；不以沉没成本维持计划。 | H9: 未开始
A10: 拿到可行offer后 | D10: HR确认实际签约主体、认可雇主、工资口径、合同、办理责任及入职条件。 | E10: 安排夫妻材料、公证翻译、附加证明书；核对同步申请与住房。 | F10: 聘用与居留条件清楚，单收入预算可接受；申请材料按当时官方清单。 | G10: 预留材料和审批时间；官方决定期与实际办理可能不同，以HR及IND为准。 | H10: 未开始
A11: 获批及落地阶段 | D11: 完成入职和必要登记，核对居留卡与工作权、保险等。 | E11: 妻子取得相应居留；开始当地求职和荷兰语入门。 | F11: 每项落地手续有凭证；保留合同、工资及居留记录。 | G11: 辞职、出行与入职安排结合批准及合同生效条件落实。 | H11: 未开始
A12: 落地第1—2年 | D12: 稳定工作，按需提升技术和荷兰语；记录换雇主、续签及出入境。 | E12: 妻子规划自己的就业和学习；双方核对融入考试适用情况。 | F12: 逐步完成A1/A2学习；按届时规则安排完整融入考试。 | G12: 失业、换岗及时核对居留规则；提前准备续签。 | H12: 未开始
A13: 接近5年居留时 | D13: 按本人居留起算日复核长期居留或永居资格与收入。 | E13: 妻子单独核对自己的起算日、连续居留及考试等条件。 | F13: 符合届时全部规则后申请；不能只凭满5年或A2语言证书判断。 | G13: 若2027年开始合格居留，可约在2032年复核；这只是示例。 | H13: 未开始
A15: 节奏说明 | B15: 时间均为规划假设 | C15: 投递数量 | D15: 建议范围，按合适空缺调整 | E15: 不要求 | F15: 为凑数量投不匹配岗位 | G15: 结果 | H15: 面试与offer不能保证

Sheet 语言与周计划
A1: 语言与周计划
A2: 目标性质 | B2: 以下均为学习建议 | C2: 官方要求 | D2: HSM没有统一雅思门槛 | E2: 记录方法 | F2: 浅黄色填写实际值 | G2: 分钟→小时用公式
A4: 对象或阶段 | B4: 建议能力目标 | C4: 可选分数标尺 | D4: 实际验收 | E4: 学习重点 | F4: 何时复盘 | G4: 说明
A5: 丈夫：第1—2周 | B5: 录制自我介绍和项目讲解，做听说摸底 | C5: 未知；先测再定 | D5: 保存录音与测评，明确听力、口语、词汇短板 | E5: 听懂常见工作对话；不以六级换算 | F5: 第2周 | G5: 无签证积分
A6: 丈夫：第8周 | B6: 3分钟自我介绍＋10分钟项目介绍 | C6: 无需正式考试 | D6: 能解释职责、系统构成、技术困难和结果 | E6: 听力与口语；常用技术表达 | F6: 第8周 | G6: 可同步投递
A7: 丈夫：第14周 | B7: 30分钟技术交流并回答追问 | C7: 可做一次模拟，记录四项 | D7: 能讲故障定位和设计取舍；听不懂时会澄清 | E7: 英文技术面试＋简历项目 | F7: 第14周 | G7: 非考试过线
A8: 丈夫：第26周 | B8: 约45分钟技术模拟，能跟进需求讨论 | C8: 建议参考：总分6.5；听力7.0；口语6.5；阅读/写作各≥6.0 | D8: 请老师或有面试经验者反馈；分数不能替代工作沟通 | E8: 按真实面试失分项改进 | F8: 第26周 | G8: 分数仅为规划标尺
A9: 妻子：第26周 | B9: 日常事务＋20分钟运营工作交流 | C9: 可选参考：总分6.0、口语6.0 | D9: 解释工作任务、数据或协作实例；不要求先拿offer | E9: 生活英语、运营词汇和沟通 | F9: 每8周 | G9: 不是随行条件
A10: 夫妻：确定赴荷后 | B10: 荷兰语逐步A1→A2，按需要继续B1 | C10: A1/A2/B1是能力等级，不是雅思分数 | D10: 永居须按届时要求完成融入考试或豁免 | E10: 当地生活、实际考试模块 | F10: 落地后每半年 | G10: 当前A2要求见路线表
A12: 星期 | B12: 丈夫训练内容 | C12: 妻子训练内容 | D12: 练习产出 | E12: 求职安排 | F12: 丈夫分钟 | G12: 妻子分钟
A13: 周一 | B13: 精听20＋跟读20＋项目表达20 | C13: 生活听力20＋口语20 | D13: 一段2分钟录音 | E13: 求职另计 | F13: 60 | G13: 40
A14: 周二 | B14: 听力20＋技术问答30＋复盘10 | C14: 工作词汇20＋工作介绍20 | D14: 一次技术问题回答 | E14: 求职另计 | F14: 60 | G14: 40
A15: 周三 | B15: 听力20＋对话30＋复盘10 | C15: 听力20＋对话20 | D15: 一次澄清与追问练习 | E15: 求职另计 | F15: 60 | G15: 40
A16: 周四 | B16: 技术材料20＋口述30＋短邮件10 | C16: 运营案例20＋表达20 | D16: 一封英文工作邮件 | E16: 求职另计 | F16: 60 | G16: 40
A17: 周五 | B17: 听力20＋本周错题20＋自由表达20 | C17: 生活场景20＋本周复盘20 | D17: 修正本周常见错误 | E17: 求职另计 | F17: 60 | G17: 40
A18: 周六 | B18: 项目/技术模拟45＋反馈45 | C18: 运营工作对话30＋反馈30 | D18: 一次模拟交流 | E18: 另安排60分钟筛选与投递 | F18: 90 | G18: 60
A19: 周日 | B19: 复盘30＋听说综合60 | C19: 复盘20＋生活交流20 | D19: 下周重点与录音对比 | E19: 另安排60分钟求职复盘 | F19: 90 | G19: 40
A20: 每周英语总计 | B20: 计划建议；不是达到目标所需的保证学时 | C20: 求职另加：丈夫每周2小时 | D20: 丈夫小时 | E20: 妻子小时 | F20: =SUM(F13:F19)/60 -> 8 | G20: =SUM(G13:G19)/60 -> 5
A22: 记录示例（不计入） | B22: 2026-09-21 当周 | C22: 实际训练：480分钟/300分钟 | D22: 录音已保存 | E22: 根据反馈补听力 | F22: 8 | G22: 5
A24: 周次 | B24: 周开始日 | C24: 丈夫实际分钟 | D24: 妻子实际分钟 | E24: 本周结果或瓶颈 | F24: 丈夫实际小时 | G24: 妻子实际小时
A25: 1 | B25: =路线与门槛!$D$2+(A25-1)*7 -> 46286 | F25: =IF(C25="","",C25/60) | G25: =IF(D25="","",D25/60)
A26: 2 | B26: =路线与门槛!$D$2+(A26-1)*7 -> 46293 | F26: =IF(C26="","",C26/60) | G26: =IF(D26="","",D26/60)
A27: 3 | B27: =路线与门槛!$D$2+(A27-1)*7 -> 46300 | F27: =IF(C27="","",C27/60) | G27: =IF(D27="","",D27/60)
A28: 4 | B28: =路线与门槛!$D$2+(A28-1)*7 -> 46307 | F28: =IF(C28="","",C28/60) | G28: =IF(D28="","",D28/60)
A29: 5 | B29: =路线与门槛!$D$2+(A29-1)*7 -> 46314 | F29: =IF(C29="","",C29/60) | G29: =IF(D29="","",D29/60)
A30: 6 | B30: =路线与门槛!$D$2+(A30-1)*7 -> 46321 | F30: =IF(C30="","",C30/60) | G30: =IF(D30="","",D30/60)
A31: 7 | B31: =路线与门槛!$D$2+(A31-1)*7 -> 46328 | F31: =IF(C31="","",C31/60) | G31: =IF(D31="","",D31/60)
A32: 8 | B32: =路线与门槛!$D$2+(A32-1)*7 -> 46335 | F32: =IF(C32="","",C32/60) | G32: =IF(D32="","",D32/60)
A33: 9 | B33: =路线与门槛!$D$2+(A33-1)*7 -> 46342 | F33: =IF(C33="","",C33/60) | G33: =IF(D33="","",D33/60)
A34: 10 | B34: =路线与门槛!$D$2+(A34-1)*7 -> 46349 | F34: =IF(C34="","",C34/60) | G34: =IF(D34="","",D34/60)
A35: 11 | B35: =路线与门槛!$D$2+(A35-1)*7 -> 46356 | F35: =IF(C35="","",C35/60) | G35: =IF(D35="","",D35/60)
A36: 12 | B36: =路线与门槛!$D$2+(A36-1)*7 -> 46363 | F36: =IF(C36="","",C36/60) | G36: =IF(D36="","",D36/60)
... A50: 26 | B50: =路线与门槛!$D$2+(A50-1)*7 -> 46461 | F50: =IF(C50="","",C50/60) | G50: =IF(D50="","",D50/60)
A52: 累计实际小时 | B52: 空白保留为未知；示例不计入 | E52: 仅统计填写记录 | F52: =IF(COUNT(C25:C50)=0,"",SUM(C25:C50)/60) | G52: =IF(COUNT(D25:D50)=0,"",SUM(D25:D50)/60)

Sheet 材料清单
A1: 材料清单
A2: 适用原则 | B2: 先整理现有资料 | C2: 办理原则 | D2: 正式清单由HR、IND及市政确认 | E2: 费用时点 | F2: 公证翻译按实际要求办理，避免过早开有时效文件。 | G2: 状态 | H2: 初始均待确认
A4: 用途 | B4: 准备内容 | C4: 负责人 | D4: 准备时点 | E4: 具体要求或成果 | F4: 注意事项 | G4: 状态 | H4: 依据
A5: 求职 | B5: 英文简历 | C5: 丈夫 | D5: 前2周 | E5: 约2页，清楚列出职责、任职年月、技术栈及本人贡献。 | F5: 页数为建议；成绩与职责真实。 | G5: 待确认 | H5: 规划建议
A6: 求职 | B6: 项目案例2—3个 | C6: 丈夫 | D6: 第1—8周 | E6: 准备系统架构、个人贡献、故障定位、验证及交付实例。 | F6: 用脱敏描述；不提交公司代码或保密资料。 | G6: 待确认 | H6: 规划建议
A7: 求职 | B7: 岗位与雇主清单 | C7: 丈夫 | D7: 第1周起 | E7: 记录岗位链接、语言、薪资、签约主体、认可雇主及担保意愿。 | F7: 认可雇主资格与愿意办理是两项。 | G7: 待确认 | H7: https://ind.nl/en/public-register-recognised-sponsors
A8: 求职 | B8: 毕业证、学位证、成绩单 | C8: 夫妻 | D8: 前4周先扫描 | E8: 丈夫本科；妻子本科及硕士。若HR要求再安排核验或翻译。 | F8: 荷兰HSM不要求套用澳洲ACS或加拿大ECA。 | G8: 待确认 | H8: https://ind.nl/en/residence-permits/work/highly-skilled-migrant
A9: 求职 | B9: 任职与项目时间线 | C9: 丈夫 | D9: 前4周 | E9: 逐段列清年月、公司、岗位和工作职责；现有证明归档。 | F9: 工资、社保等仅在被要求时提交。 | G9: 待确认 | H9: 规划建议；具体依雇主要求
A10: 身份 | B10: 护照及有效期 | C10: 夫妻 | D10: 前2周 | E10: 检查现有证件与办理所需有效期，保留清晰扫描件。 | F10: 正式要求按申请时间核对。 | G10: 待确认 | H10: https://ind.nl/en/residence-permits/work/highly-skilled-migrant
A11: 家庭居留 | B11: 结婚证与关系资料 | C11: 夫妻 | D11: 前4周整理 | E11: 整理婚姻证明、姓名拼写一致性；按要求提供译文及认证。 | F11: 配偶单独申请，不因丈夫获批自动取得居留。 | G11: 待确认 | H11: https://ind.nl/en/residence-permits/family-and-partner/residence-permit-for-partner
A12: 家庭/登记 | B12: 出生资料、户口等 | C12: 夫妻 | D12: 有offer后按清单 | E12: 市政登记或关系证明可能需要；先确认原始资料是否能取得。 | F12: 夫妻出生年份可能不同，官方中国出生资料规则分情形。 | G12: 待确认 | H12: https://www.netherlandsworldwide.nl/legalisation/foreign-documents/china
A13: 认证 | B13: 公证翻译与附加证明书 | C13: 夫妻 | D13: 确认接收单位要求后 | E13: 中国文件通常按官方中国页面办理公证英文译文和附加证明书。 | F13: 不同接收单位的时效要求可能不同。 | G13: 待确认 | H13: https://www.netherlandsworldwide.nl/legalisation/foreign-documents/china
A14: 工作居留 | B14: 合同与薪资构成 | C14: 丈夫/HR | D14: 正式offer阶段 | E14: 确认每月税前可计入薪资、合同期限、岗位、雇主及工作地点。 | F14: 2027年申请前刷新门槛，不只比较奖金总包。 | G14: 待确认 | H14: https://ind.nl/en/residence-permits/work/highly-skilled-migrant https://ind.nl/en/required-amounts-income-requirements
... A21: 填写示例 | B21: 护照 | C21: 夫妻 | D21: 前2周 | E21: 已找到原件，等待核对有效期 | F21: 仅演示填写方式 | G21: 已有 | H21: 示例，不表示本人已完成

Sheet 求职跟踪
A1: 求职跟踪
A2: 填写说明 | B2: 第5行是虚构示例 | C2: 从第6行填真实岗位 | D2: 记录招聘网站原始链接 | E2: 雇主需查签约主体 | F2: 认可≠愿意办理 | G2: 工资用月薪口径 | H2: 未知保持待确认 | I2: 不以总分筛选 | J2: 按关键条件核对 | K2: 至少每两周复盘一次
A4: 投递日期 | B4: 国家/城市 | C4: 公司及签约主体 | D4: 岗位名称及链接 | E4: 核心要求匹配 | F4: 工作语言 | G4: IND认可雇主 | H4: 支持本岗位办理 | I4: 月薪欧元 | J4: 招聘进展 | K4: 反馈与下一步
B5: 荷兰/示例城市 | C5: 示例公司（虚构） | D5: Embedded Software Engineer；填实际URL | E5: C、CAN；其余待核实 | F5: 英语 | G5: 待核实 | H5: 待确认 | J5: 未投递 | K5: 示例不代表真实雇主或岗位，不计入个人投递。
A27: 复盘 | B27: 主要现象 | C27: 优先核对 | D27: 处理方式
A28: 每2周 | B28: 投递后缺少回复 | C28: 岗位匹配、简历表达、工作权与海外招聘 | D28: 请有经验者审阅简历；核实对方是否考虑海外候选人。不要仅凭少量无回复判断国家不可行。
A29: 每6—8周 | B29: 有面试但没有推进 | C29: 听说、技术深度、薪资或担保条件 | D29: 记录具体反馈；语言或技术问题定向补强，制度或岗位问题则调整雇主/备选。

Sheet Sheet1
